dynamodb_connection/__init__.py
dynamodb_connection/connection.py
dynamodb_connection/py.typed
dynamodb_connection/table_editor.py
dynamodb_connection/utils.py
st_dynamodb_connection-0.1.5.dist-info/LICENSE
st_dynamodb_connection-0.1.5.dist-info/METADATA
st_dynamodb_connection-0.1.5.dist-info/WHEEL
st_dynamodb_connection-0.1.5.dist-info/RECORD
