Metadata-Version: 2.1
Name: st-dynamodb-connection
Version: 0.1.5
Summary: Streamlit Connection for Amazon DynamoDB.
Home-page: https://github.com/mrtj/st-dynamodb-connection
License: MIT
Keywords: streamlit,dynamodb,streamlit-connection
Author: Janos Tolgyesi
Author-email: janos.tolgyesi@gmail.com
Requires-Python: >=3.8, !=2.7.*, !=3.0.*, !=3.1.*, !=3.2.*, !=3.3.*, !=3.4.*, !=3.5.*, !=3.6.*, !=3.7.*
Classifier: License :: OSI Approved :: MIT License
Classifier: Programming Language :: Python :: 3
Classifier: Programming Language :: Python :: 3.8
Classifier: Programming Language :: Python :: 3.9
Classifier: Programming Language :: Python :: 3.10
Classifier: Programming Language :: Python :: 3.11
Classifier: Programming Language :: Python :: 3.12
Requires-Dist: boto3 (>=1.28,<2.0)
Requires-Dist: dynamodb-mapping (>=0.1,<1.0)
Requires-Dist: pandas (>=2.0,<3.0)
Requires-Dist: streamlit (>=1.28,<2.0)
Project-URL: Repository, https://github.com/mrtj/st-dynamodb-connection
